odoo/addons/l10n_br_purchase_stock/README.rst
odoo/addons/l10n_br_purchase_stock/__init__.py
odoo/addons/l10n_br_purchase_stock/__manifest__.py
odoo/addons/l10n_br_purchase_stock/demo/purchase_order.xml
odoo/addons/l10n_br_purchase_stock/i18n/l10n_br_purchase_stock.pot
odoo/addons/l10n_br_purchase_stock/i18n/pt_BR.po
odoo/addons/l10n_br_purchase_stock/models/__init__.py
odoo/addons/l10n_br_purchase_stock/models/purchase_order.py
odoo/addons/l10n_br_purchase_stock/models/purchase_order_line.py
odoo/addons/l10n_br_purchase_stock/models/res_company.py
odoo/addons/l10n_br_purchase_stock/models/res_config_settings.py
odoo/addons/l10n_br_purchase_stock/models/stock_move.py
odoo/addons/l10n_br_purchase_stock/models/stock_picking.py
odoo/addons/l10n_br_purchase_stock/readme/CONFIGURE.md
odoo/addons/l10n_br_purchase_stock/readme/CONTRIBUTORS.md
odoo/addons/l10n_br_purchase_stock/readme/CREDITS.md
odoo/addons/l10n_br_purchase_stock/readme/DESCRIPTION.md
odoo/addons/l10n_br_purchase_stock/readme/HISTORY.md
odoo/addons/l10n_br_purchase_stock/readme/INSTALL.md
odoo/addons/l10n_br_purchase_stock/readme/ROADMAP.md
odoo/addons/l10n_br_purchase_stock/readme/USAGE.md
odoo/addons/l10n_br_purchase_stock/static/description/icon.png
odoo/addons/l10n_br_purchase_stock/static/description/index.html
odoo/addons/l10n_br_purchase_stock/tests/__init__.py
odoo/addons/l10n_br_purchase_stock/tests/test_l10n_br_purchase_stock.py
odoo/addons/l10n_br_purchase_stock/tests/test_stock_rule.py
odoo/addons/l10n_br_purchase_stock/views/purchase_order.xml
odoo/addons/l10n_br_purchase_stock/views/res_company_view.xml
odoo/addons/l10n_br_purchase_stock/views/res_config_settings.xml
odoo/addons/l10n_br_purchase_stock/wizards/__init__.py
odoo/addons/l10n_br_purchase_stock/wizards/stock_invocing_onshipping.py
odoo_addon_l10n_br_purchase_stock-16.0.2.0.0.dist-info/METADATA
odoo_addon_l10n_br_purchase_stock-16.0.2.0.0.dist-info/WHEEL
odoo_addon_l10n_br_purchase_stock-16.0.2.0.0.dist-info/top_level.txt
odoo_addon_l10n_br_purchase_stock-16.0.2.0.0.dist-info/RECORD
